mare/__init__.py
mare/branch.py
mare/errors.py
mare/git_utils.py
mare/main.py
mare/project.py
mare-0.1.0.dist-info/LICENSE
mare-0.1.0.dist-info/METADATA
mare-0.1.0.dist-info/WHEEL
mare-0.1.0.dist-info/entry_points.txt
mare-0.1.0.dist-info/RECORD
