Metadata-Version: 2.1
Name: mare
Version: 0.1.0
Summary: simple wirkflow manager for developeing
License: MIT
Author: Haiz14
Author-email: haiz.gigs@gmail.com
Requires-Python: >=3.11,<4.0
Classifier: License :: OSI Approved :: MIT License
Classifier: Programming Language :: Python :: 3
Classifier: Programming Language :: Python :: 3.11
Requires-Dist: Pygments (>=2.16.1,<3.0.0)
Requires-Dist: click (>=8.1.7,<9.0.0)
Requires-Dist: colorama (>=0.4.6,<0.5.0)
Requires-Dist: markdown-it-py (>=3.0.0,<4.0.0)
Requires-Dist: mdurl (>=0.1.2,<0.2.0)
Requires-Dist: rich (>=13.6.0,<14.0.0)
Requires-Dist: shellingham (>=1.5.3,<2.0.0)
Requires-Dist: typer (>=0.9.0,<0.10.0)
